AUTHORS.txt
LICENSE
MANIFEST.in
README.rst
setup.py
djangorestframework_apidoc.egg-info/PKG-INFO
djangorestframework_apidoc.egg-info/SOURCES.txt
djangorestframework_apidoc.egg-info/dependency_links.txt
djangorestframework_apidoc.egg-info/requires.txt
djangorestframework_apidoc.egg-info/top_level.txt
rest_framework_apidoc/__init__.py
rest_framework_apidoc/apidoc.py
rest_framework_apidoc/mixins.py
rest_framework_apidoc/monkey.py
tests/__init__.py
tests/models.py
tests/settings.py
tests/tests.py