Metadata-Version: 1.1
Name: djangorestframework-apidoc
Version: 0.0.1
Summary: Modular documentation generator for rest framwork apis
Home-page: https://github.com/kaleidos/djangorestframework-apidoc
Author: Jesús Espino García
Author-email: jespinog@gmail.com
License: BSD
Keywords: django,api,rest,doc
Platform: UNKNOWN
Classifier: Programming Language :: Python
Classifier: Development Status :: 4 - Beta
Classifier: Framework :: Django
Classifier: Intended Audience :: Developers
Classifier: License :: OSI Approved :: BSD License
Classifier: Operating System :: OS Independent
Classifier: Programming Language :: Python
Classifier: Topic :: Internet :: WWW/HTTP
